{
    "columns": [
        {
            "field": "kode_rak_storage",
            "headerText": "Kode Rak Storage",
            "type": "string",
            "format": "",
            "textAlign": "left",
            "visible": true,
            "editType": "defaultEdit"
        },
        {
            "field": "nama_rak_storage",
            "headerText": "Nama Rak Storage",
            "type": "string",
            "format": "",
            "textAlign": "left",
            "visible": true,
            "editType": "defaultEdit"
        },
        {
            "field": "nama_stockroom",
            "headerText": "Nama Stockroom",
            "type": "string",
            "format": "",
            "textAlign": "left",
            "visible": true,
            "editType": "defaultEdit"
        },
        {
            "field": "nama_penanggung_jawab_rak_storage",
            "headerText": "Nama Penanggung Jawab",
            "type": "string",
            "format": "",
            "textAlign": "left",
            "visible": true,
            "editType": "defaultEdit"
        }
    ],
    "filter": [
        {
            "field": "msars.kode_rak_storage",
            "filter": "like",
            "title": "Kode Rak Storage"
        },
        {
            "field": "msars.nama_rak_storage",
            "filter": "like",
            "title": "Nama Rak Storage"
        },
        {
            "field": "mss.nama_stockroom",
            "filter": "like",
            "title": "Nama Stockroom"
        },
        {
            "field": "msapjrs.nama_penanggung_jawab_rak_storage",
            "filter": "like",
            "title": "Nama Penanggung Jawab"
        }
    ]
}